high_order_implicit_representation/__init__.py
high_order_implicit_representation/networks.py
high_order_implicit_representation/random_sample_dataset.py
high_order_implicit_representation/rendering.py
high_order_implicit_representation/single_image_dataset.py
high_order_implicit_representation/utils.py
high_order_implicit_representation-0.2.0.dist-info/LICENSE
high_order_implicit_representation-0.2.0.dist-info/WHEEL
high_order_implicit_representation-0.2.0.dist-info/METADATA
high_order_implicit_representation-0.2.0.dist-info/RECORD
