Metadata-Version: 2.1
Name: high-order-implicit-representation
Version: 0.2.0
Summary: 
License: MIT
Author: John Loverich
Author-email: john.loverich@gmail.com
Requires-Python: >=3.9,<4.0
Classifier: License :: OSI Approved :: MIT License
Classifier: Programming Language :: Python :: 3
Classifier: Programming Language :: Python :: 3.10
Classifier: Programming Language :: Python :: 3.9
Requires-Dist: Pillow (>=9.1.1,<10.0.0)
Requires-Dist: high-order-layers-torch (>=1.1.18,<2.0.0)
Requires-Dist: hydra-core (>=1.2.0,<2.0.0)
Requires-Dist: hydra-nevergrad-sweeper (==1.3.0.dev0)
Requires-Dist: matplotlib (>=3.5.2,<4.0.0)
Requires-Dist: omegaconf (>=2.2.2,<3.0.0)
Requires-Dist: pytorch-lightning (>=1.8.3,<2.0.0)
Requires-Dist: scikit-image (>=0.19.3,<0.20.0)
Requires-Dist: torch (>=1.13.0,<2.0.0)
Requires-Dist: torch-optimizer (>=0.3.0,<0.4.0)
Requires-Dist: torchsummary (>=1.5.1,<2.0.0)
Requires-Dist: torchvision (>=0.14.0,<0.15.0)
